abayes/__init__.py
abayes/config.py
abayes/data.py
abayes/models.py
abayes/plotting.py
abayes/results.py
abayes/test.py
abayes-0.0.2.dist-info/METADATA
abayes-0.0.2.dist-info/WHEEL
abayes-0.0.2.dist-info/RECORD
